bulker/__init__.py
bulker/_version.py
bulker/bulker.py
bulker/templates/bulker_config.yaml
bulker/templates/docker_build.jinja2
bulker/templates/docker_executable.jinja2
bulker/templates/docker_shell.jinja2
bulker/templates/singularity_build.jinja2
bulker/templates/singularity_executable.jinja2
bulker/templates/singularity_shell.jinja2
bulker/templates/start.sh
bulker/templates/start_strict.sh
bulker/templates/zsh_start/.zshrc
bulker/templates/zsh_start_strict/.zshrc
bulker-0.7.3.dist-info/LICENSE.txt
bulker-0.7.3.dist-info/METADATA
bulker-0.7.3.dist-info/WHEEL
bulker-0.7.3.dist-info/entry_points.txt
bulker-0.7.3.dist-info/top_level.txt
bulker-0.7.3.dist-info/RECORD
