Metadata-Version: 2.1
Name: bulker
Version: 0.7.3
Summary: Manager of portable multi-container computing environments
Home-page: https://bulker.databio.org
Author: Nathan Sheffield
Author-email: nathan@code.databio.org
License: BSD2
Keywords: docker,containers,reproducibility,bioinformatics,workflow
Platform: UNKNOWN
Classifier: Development Status :: 4 - Beta
Classifier: License :: OSI Approved :: BSD License
Classifier: Programming Language :: Python :: 3.6
Classifier: Programming Language :: Python :: 3.7
Classifier: Topic :: Scientific/Engineering :: Bio-Informatics
License-File: LICENSE.txt
Requires-Dist: yacman (>=0.8.4)
Requires-Dist: pyyaml (>=5.1)
Requires-Dist: logmuse (>=0.2.0)
Requires-Dist: jinja2
Requires-Dist: ubiquerg (>=0.5.1)
Requires-Dist: psutil
